rugosa/__init__.py
rugosa/disassembly.py
rugosa/func_utils.py
rugosa/function_creator.py
rugosa/re.py
rugosa/shell.py
rugosa/strings.py
rugosa/yara.py
rugosa/emulation/__init__.py
rugosa/emulation/actions.py
rugosa/emulation/constants.py
rugosa/emulation/cpu_context.py
rugosa/emulation/emulator.py
rugosa/emulation/exceptions.py
rugosa/emulation/flowchart.py
rugosa/emulation/functions.py
rugosa/emulation/instruction.py
rugosa/emulation/memory.py
rugosa/emulation/objects.py
rugosa/emulation/opcode.py
rugosa/emulation/operands.py
rugosa/emulation/registers.py
rugosa/emulation/registry.py
rugosa/emulation/utils.py
rugosa/emulation/variables.py
rugosa/emulation/ARM/__init__.py
rugosa/emulation/ARM/instruction.py
rugosa/emulation/ARM/opcodes.py
rugosa/emulation/ARM/operands.py
rugosa/emulation/ARM/registers.py
rugosa/emulation/ARM/utils.py
rugosa/emulation/call_hooks/__init__.py
rugosa/emulation/call_hooks/stdlib/__init__.py
rugosa/emulation/call_hooks/stdlib/libc.py
rugosa/emulation/call_hooks/win_api/__init__.py
rugosa/emulation/call_hooks/win_api/advapi32.py
rugosa/emulation/call_hooks/win_api/kernel32.py
rugosa/emulation/call_hooks/win_api/shell32.py
rugosa/emulation/call_hooks/win_api/shlwapi.py
rugosa/emulation/call_hooks/win_api/win_constants.py
rugosa/emulation/call_hooks/win_api/ws2_32.py
rugosa/emulation/x86_64/__init__.py
rugosa/emulation/x86_64/fpu_opcodes.py
rugosa/emulation/x86_64/instruction.py
rugosa/emulation/x86_64/opcodes.py
rugosa/emulation/x86_64/operands.py
rugosa/emulation/x86_64/registers.py
rugosa/ghidra_plugin/__init__.py
rugosa/ghidra_plugin/install.py
rugosa/ghidra_plugin/components/__init__.py
rugosa/ghidra_plugin/components/actions.py
rugosa/ghidra_plugin/components/call_history.py
rugosa/ghidra_plugin/components/emulator.py
rugosa/ghidra_plugin/components/function_arguments.py
rugosa/ghidra_plugin/components/memory.py
rugosa/ghidra_plugin/components/operands.py
rugosa/ghidra_plugin/components/registers.py
rugosa-1.0.0.dist-info/LICENSE.txt
rugosa-1.0.0.dist-info/METADATA
rugosa-1.0.0.dist-info/WHEEL
rugosa-1.0.0.dist-info/entry_points.txt
rugosa-1.0.0.dist-info/top_level.txt
rugosa-1.0.0.dist-info/RECORD
