Metadata-Version: 2.1
Name: rugosa
Version: 1.0.0
Summary: The next generation of kordesii. This is a library for managing emulation and provides utilities for interfacing with decompiled malware samples using dragodis.
Home-page: https://github.com/Defense-Cyber-Crime-Center/rugosa
Author: DC3
License: MIT
Keywords: malware,ida,ghidra,emulation,strings
Classifier: Development Status :: 2 - Pre-Alpha
Classifier: Intended Audience :: Developers
Classifier: License :: OSI Approved :: MIT License
Classifier: Programming Language :: Python :: 3
Classifier: Programming Language :: Python :: 3.9
Classifier: Programming Language :: Python :: 3.10
Classifier: Programming Language :: Python :: 3.11
Classifier: Programming Language :: Python :: 3.12
Requires-Python: >=3.9
License-File: LICENSE.txt
Requires-Dist: dragodis >=0.8.0
Requires-Dist: cmd2 >=2
Requires-Dist: tabulate
Requires-Dist: hexdump
Requires-Dist: pyhidra >=0.6.0
Requires-Dist: yara-python
Requires-Dist: pyreadline3 ; sys_platform == "win32"
Provides-Extra: testing
Requires-Dist: pytest >=3.0.0 ; extra == 'testing'
